linkrpy.py
linkrapi-1.0.0.dist-info/WHEEL
linkrapi-1.0.0.dist-info/METADATA
linkrapi-1.0.0.dist-info/RECORD
